<?xml version="1.0" ?>
<!DOCTYPE PubmedArticleSet PUBLIC "-//NLM//DTD PubMedArticle, 1st January 2024//EN" "https://dtd.nlm.nih.gov/ncbi/pubmed/out/pubmed_240101.dtd">
<PubmedArticleSet>
<PubmedArticle><MedlineCitation Status="MEDLINE" Owner="NLM" IndexingMethod="Automated"><PMID Version="1">38641377</PMID><DateCompleted><Year>2024</Year><Month>04</Month><Day>22</Day></DateCompleted><DateRevised><Year>2024</Year><Month>04</Month><Day>22</Day></DateRevised><Article PubModel="Print-Electronic"><Journal><ISSN IssnType="Electronic">1532-8201</ISSN><JournalIssue CitedMedium="Internet"><Volume>76</Volume><PubDate><Year>2024</Year><Month>Apr</Month></PubDate></JournalIssue><Title>Applied nursing research : ANR</Title><ISOAbbreviation>Appl Nurs Res</ISOAbbreviation></Journal><ArticleTitle>Educational content and strategies to support nurses from culturally and linguistically diverse backgrounds caring for patients considering voluntary assisted dying: The Australian experience.</ArticleTitle><Pagination><StartPage>151765</StartPage><MedlinePgn>151765</MedlinePgn></Pagination><ELocationID EIdType="doi" ValidYN="Y">10.1016/j.apnr.2024.151765</ELocationID><ELocationID EIdType="pii" ValidYN="Y">S0897-1897(24)00003-X</ELocationID><Abstract><AbstractText Label="OBJECTIVES" NlmCategory="OBJECTIVE">Drawing on findings from a qualitative study that aimed to explore the knowledge and attitudes of nurses from culturally and linguistically diverse (CALD) backgrounds about voluntary assisted dying (VAD). The study also aimed to identify the strategies that assist nurses in their readiness and preparation for exposure to VAD. This paper reports on the educational content and strategies that could assist nurses from CALD backgrounds to be better prepared when they encounter VAD requests.</AbstractText><AbstractText Label="BACKGROUND" NlmCategory="BACKGROUND">Around the world, healthcare professionals have roles to play in caring for patients requesting voluntary assisted dying. Nurses, particularly those from diverse geographic and clinical settings, have voiced inadequate knowledge and understanding about voluntary assisted dying.</AbstractText><AbstractText Label="DESIGN" NlmCategory="METHODS">A qualitative descriptive approach was undertaken.</AbstractText><AbstractText Label="METHODS" NlmCategory="METHODS">Data collection involved one focus group and 16 in-depth interviews. A total of 21 nurses from CALD backgrounds were recruited from one Australian state. Thematic analysis was conducted to interpret the data.</AbstractText><AbstractText Label="FINDINGS" NlmCategory="RESULTS">Nurses identified their knowledge gaps and specified the need for education and workplace training on VAD, its legal and ethical aspects, clarity on their role, communication techniques and how VAD intersects with their practice. They suggested various teaching strategies that could prepare nurses to work safely and confidently in a clinical environment where voluntary assisted dying is an option for patients.</AbstractText><AbstractText Label="CONCLUSION" NlmCategory="CONCLUSIONS">Given the high number of nurses from diverse backgrounds working in the Australian health sector, these nurses need to be fully prepared to care for patients requesting VAD.</AbstractText><CopyrightInformation>Copyright &#xa9; 2024 The Authors. Published by Elsevier Inc. All rights reserved.</CopyrightInformation></Abstract><AuthorList CompleteYN="Y"><Author ValidYN="Y"><LastName>Malik</LastName><ForeName>Gulzar</ForeName><Initials>G</Initials><AffiliationInfo><Affiliation>School of Nursing and Midwifery, La Trobe University, Australia. Electronic address: g.malik@latrobe.edu.au.</Affiliation></AffiliationInfo></Author><Author ValidYN="Y"><LastName>Penman</LastName><ForeName>Joy</ForeName><Initials>J</Initials><AffiliationInfo><Affiliation>School of Nursing and Midwifery, Monash University, Australia.</Affiliation></AffiliationInfo></Author><Author ValidYN="Y"><LastName>Rogerson</LastName><ForeName>Kelly</ForeName><Initials>K</Initials><AffiliationInfo><Affiliation>Palliative Care South East, Australia. Electronic address: kelly.rogerson@palliativecarese.org.au.</Affiliation></AffiliationInfo></Author><Author ValidYN="Y"><LastName>Murphy</LastName><ForeName>Julie</ForeName><Initials>J</Initials><AffiliationInfo><Affiliation>Palliative Care South East, Australia. Electronic address: julie.murphy@palliativecarese.org.au.</Affiliation></AffiliationInfo></Author><Author ValidYN="Y"><LastName>Zhong</LastName><ForeName>Yaping</ForeName><Initials>Y</Initials><AffiliationInfo><Affiliation>School of Nursing and Midwifery, Monash University, Australia.</Affiliation></AffiliationInfo></Author><Author ValidYN="Y"><LastName>Johnson</LastName><ForeName>Claire E</ForeName><Initials>CE</Initials><AffiliationInfo><Affiliation>Palliative and Supportive Care, Eastern Health, Melbourne, Australia; Australian Health Services Research Institute, University of Wollongong, Wollongong, Australia. Electronic address: jclaire@uow.edu.au.</Affiliation></AffiliationInfo></Author></AuthorList><Language>eng</Language><PublicationTypeList><PublicationType UI="D016428">Journal Article</PublicationType></PublicationTypeList><ArticleDate DateType="Electronic"><Year>2024</Year><Month>02</Month><Day>19</Day></ArticleDate></Article><MedlineJournalInfo><Country>United States</Country><MedlineTA>Appl Nurs Res</MedlineTA><NlmUniqueID>8901557</NlmUniqueID><ISSNLinking>0897-1897</ISSNLinking></MedlineJournalInfo><CitationSubset>IM</CitationSubset><MeshHeadingList><MeshHeading><DescriptorName UI="D006801" MajorTopicYN="N">Humans</DescriptorName></MeshHeading><MeshHeading><DescriptorName UI="D001315" MajorTopicYN="N" Type="Geographic">Australia</DescriptorName></MeshHeading><MeshHeading><DescriptorName UI="D017236" MajorTopicYN="Y">Suicide, Assisted</DescriptorName></MeshHeading><MeshHeading><DescriptorName UI="D006282" MajorTopicYN="N">Health Personnel</DescriptorName></MeshHeading><MeshHeading><DescriptorName UI="D017144" MajorTopicYN="N">Focus Groups</DescriptorName></MeshHeading><MeshHeading><DescriptorName UI="D036301" MajorTopicYN="N">Qualitative Research</DescriptorName></MeshHeading></MeshHeadingList><KeywordList Owner="NOTNLM"><Keyword MajorTopicYN="N">Culturally and linguistically diverse backgrounds</Keyword><Keyword MajorTopicYN="N">Education</Keyword><Keyword MajorTopicYN="N">Internationally qualified nurses</Keyword><Keyword MajorTopicYN="N">Nurses' preparation</Keyword><Keyword MajorTopicYN="N">Qualified overseas nurses</Keyword><Keyword MajorTopicYN="N">Voluntary assisted dying</Keyword></KeywordList><CoiStatement>Declaration of competing interest The authors declare no conflict of interest.</CoiStatement></MedlineCitation><PubmedData><History><PubMedPubDate PubStatus="received"><Year>2023</Year><Month>1</Month><Day>3</Day></PubMedPubDate><PubMedPubDate PubStatus="revised"><Year>2023</Year><Month>8</Month><Day>22</Day></PubMedPubDate><PubMedPubDate PubStatus="accepted"><Year>2024</Year><Month>2</Month><Day>18</Day></PubMedPubDate><PubMedPubDate PubStatus="medline"><Year>2024</Year><Month>4</Month><Day>22</Day><Hour>6</Hour><Minute>42</Minute></PubMedPubDate><PubMedPubDate PubStatus="pubmed"><Year>2024</Year><Month>4</Month><Day>20</Day><Hour>0</Hour><Minute>42</Minute></PubMedPubDate><PubMedPubDate PubStatus="entrez"><Year>2024</Year><Month>4</Month><Day>19</Day><Hour>20</Hour><Minute>57</Minute></PubMedPubDate></History><PublicationStatus>ppublish</PublicationStatus><ArticleIdList><ArticleId IdType="pubmed">38641377</ArticleId><ArticleId IdType="doi">10.1016/j.apnr.2024.151765</ArticleId><ArticleId IdType="pii">S0897-1897(24)00003-X</ArticleId></ArticleIdList></PubmedData></PubmedArticle></PubmedArticleSet>