<?xml version="1.0" ?>
<!DOCTYPE PubmedArticleSet PUBLIC "-//NLM//DTD PubMedArticle, 1st January 2024//EN" "https://dtd.nlm.nih.gov/ncbi/pubmed/out/pubmed_240101.dtd">
<PubmedArticleSet>
<PubmedArticle><MedlineCitation Status="MEDLINE" Owner="NLM" IndexingMethod="Automated"><PMID Version="1">39160544</PMID><DateCompleted><Year>2024</Year><Month>08</Month><Day>19</Day></DateCompleted><DateRevised><Year>2024</Year><Month>08</Month><Day>22</Day></DateRevised><Article PubModel="Electronic"><Journal><ISSN IssnType="Electronic">1472-684X</ISSN><JournalIssue CitedMedium="Internet"><Volume>23</Volume><Issue>1</Issue><PubDate><Year>2024</Year><Month>Aug</Month><Day>19</Day></PubDate></JournalIssue><Title>BMC palliative care</Title><ISOAbbreviation>BMC Palliat Care</ISOAbbreviation></Journal><ArticleTitle>Non-invasive technology to assess hydration status in advanced cancer to explore relationships between fluid status and symptoms: an observational study using bioelectrical impedance analysis.</ArticleTitle><Pagination><StartPage>209</StartPage><MedlinePgn>209</MedlinePgn></Pagination><ELocationID EIdType="pii" ValidYN="Y">209</ELocationID><ELocationID EIdType="doi" ValidYN="Y">10.1186/s12904-024-01542-z</ELocationID><Abstract><AbstractText Label="BACKGROUND" NlmCategory="BACKGROUND">Oral fluid intake decreases in advanced cancer in the dying phase of illness. There is inadequate evidence to support the assessment, and management, of hydration in the dying. Bioelectrical impedance analysis (BIA) is a body composition assessment tool. BIA has the potential to inform clinal management in advanced cancer, by examining the relationships between hydration status and clinical variables.</AbstractText><AbstractText Label="AIM" NlmCategory="OBJECTIVE">BIA was used to determine the association between hydration status, symptoms, clinical signs, quality-of-life and survival in advanced cancer, including those who are dying (i.e. in the last week of life).</AbstractText><AbstractText Label="MATERIALS AND METHODS" NlmCategory="METHODS">We conducted a prospective observational study of people with advanced cancer in three centres. Advance consent methodology was used to conduct hydration assessments in the dying. Total body water was estimated using the BIA Impedance index (Height - H (m)<sup>2</sup> /Resistance - R (Ohms)). Backward regression was used to identify factors (physical signs, symptoms, quality of life) that predicted H<sup>2</sup>/R. Participants in the last 7 days of life were further assessed with BIA to assess hydration changes, and its relationship with clinical outcomes.</AbstractText><AbstractText Label="RESULTS" NlmCategory="RESULTS">One hundred and twenty-five people participated (males n&#x2009;=&#x2009;74 (59.2%), females, n&#x2009;=&#x2009;51 (40.8%)). We used backward regression analysis to describe a statistical model to predict hydration status in advanced cancer. The model demonstrated that 'less hydration' (lower H<sup>2</sup>/R) was associated with female sex (Beta = -0.39, p&#x2009;&lt;&#x2009;0.001), increased appetite (Beta = -0.12, p&#x2009;=&#x2009;0.09), increased dehydration assessment scale score (dry mouth, dry axilla, sunken eyes - Beta = -0.19, p&#x2009;=&#x2009;0.006), and increased breathlessness (Beta = -0.15, p&#x2009;=&#x2009;0.03). 'More hydration' (higher H<sup>2</sup>/R) was associated with oedema (Beta&#x2009;=&#x2009;0.49, p&#x2009;&lt;&#x2009;0.001). In dying participants (n&#x2009;=&#x2009;18, 14.4%), hydration status (H<sup>2</sup>/R) was not significantly different compared to their baseline measurements (n&#x2009;=&#x2009;18, M&#x2009;=&#x2009;49.6, SD&#x2009;=&#x2009;16.0 vs. M&#x2009;=&#x2009;51.0, SD&#x2009;=&#x2009;12.1; t(17)&#x2009;=&#x2009;0.64, p&#x2009;=&#x2009;0.53) and was not significantly associated with agitation (r<sub>s</sub> = -0.85, p&#x2009;=&#x2009;0.74), pain (r<sub>s</sub> = 0.31, p&#x2009;=&#x2009;0.23) or respiratory tract secretions (r<sub>s</sub> = -0.34, p&#x2009;=&#x2009;0.19).</AbstractText><AbstractText Label="CONCLUSIONS" NlmCategory="CONCLUSIONS">This is the first study to use bioimpedance to report a model (using clinical factors) to predict hydration status in advanced cancer. Our data demonstrates the feasibility of using an advance consent method to conduct research in dying people. This method can potentially improve the evidence base (and hence, quality of care) for the dying. Future BIA research can involve hydration assessment of cancers (according to type and stage) and associated variables (e.g., stage of illness, ethnicity and gender). Further work can use BIA to identify clinically relevant outcomes for hydration studies and establish a core outcome set to evaluate how hydration affects symptoms and quality-of-life in cancer.</AbstractText><CopyrightInformation>&#xa9; 2024. The Author(s).</CopyrightInformation></Abstract><AuthorList CompleteYN="Y"><Author ValidYN="Y"><LastName>Nwosu</LastName><ForeName>Amara Callistus</ForeName><Initials>AC</Initials><AffiliationInfo><Affiliation>Lancaster Medical School, Lancaster University, Lancaster, UK. a.nwosu@lancaster.ac.uk.</Affiliation></AffiliationInfo><AffiliationInfo><Affiliation>Liverpool University Hospitals NHS Foundation Trust, Liverpool, UK. a.nwosu@lancaster.ac.uk.</Affiliation></AffiliationInfo><AffiliationInfo><Affiliation>Marie Curie Hospice Liverpool, Liverpool, UK. a.nwosu@lancaster.ac.uk.</Affiliation></AffiliationInfo><AffiliationInfo><Affiliation>Palliative Care Unit, University of Liverpool, Liverpool, UK. a.nwosu@lancaster.ac.uk.</Affiliation></AffiliationInfo></Author><Author ValidYN="Y"><LastName>Stanley</LastName><ForeName>Sarah</ForeName><Initials>S</Initials><AffiliationInfo><Affiliation>Marie Curie Hospice Liverpool, Liverpool, UK.</Affiliation></AffiliationInfo><AffiliationInfo><Affiliation>Liverpool John Moores University, Liverpool, UK.</Affiliation></AffiliationInfo></Author><Author ValidYN="Y"><LastName>Mayland</LastName><ForeName>Catriona R</ForeName><Initials>CR</Initials><AffiliationInfo><Affiliation>Palliative Care Unit, University of Liverpool, Liverpool, UK.</Affiliation></AffiliationInfo><AffiliationInfo><Affiliation>University of Sheffield, Sheffield, UK.</Affiliation></AffiliationInfo><AffiliationInfo><Affiliation>Sheffield Teaching Hospitals NHS Foundation Trust, Sheffield, UK.</Affiliation></AffiliationInfo></Author><Author ValidYN="Y"><LastName>Mason</LastName><ForeName>Stephen</ForeName><Initials>S</Initials><AffiliationInfo><Affiliation>Palliative Care Unit, University of Liverpool, Liverpool, UK.</Affiliation></AffiliationInfo></Author><Author ValidYN="Y"><LastName>McDougall</LastName><ForeName>Alexandra</ForeName><Initials>A</Initials><AffiliationInfo><Affiliation>Clatterbridge Cancer Centre NHS Foundation Trust, Liverpool, UK.</Affiliation></AffiliationInfo></Author><Author ValidYN="Y"><LastName>Ellershaw</LastName><ForeName>John E</ForeName><Initials>JE</Initials><AffiliationInfo><Affiliation>Liverpool University Hospitals NHS Foundation Trust, Liverpool, UK.</Affiliation></AffiliationInfo><AffiliationInfo><Affiliation>Palliative Care Unit, University of Liverpool, Liverpool, UK.</Affiliation></AffiliationInfo></Author></AuthorList><Language>eng</Language><PublicationTypeList><PublicationType UI="D016428">Journal Article</PublicationType><PublicationType UI="D064888">Observational Study</PublicationType></PublicationTypeList><ArticleDate DateType="Electronic"><Year>2024</Year><Month>08</Month><Day>19</Day></ArticleDate></Article><MedlineJournalInfo><Country>England</Country><MedlineTA>BMC Palliat Care</MedlineTA><NlmUniqueID>101088685</NlmUniqueID><ISSNLinking>1472-684X</ISSNLinking></MedlineJournalInfo><CitationSubset>IM</CitationSubset><MeshHeadingList><MeshHeading><DescriptorName UI="D006801" MajorTopicYN="N">Humans</DescriptorName></MeshHeading><MeshHeading><DescriptorName UI="D017097" MajorTopicYN="Y">Electric Impedance</DescriptorName></MeshHeading><MeshHeading><DescriptorName UI="D005260" MajorTopicYN="N">Female</DescriptorName></MeshHeading><MeshHeading><DescriptorName UI="D008297" MajorTopicYN="N">Male</DescriptorName></MeshHeading><MeshHeading><DescriptorName UI="D009369" MajorTopicYN="Y">Neoplasms</DescriptorName><QualifierName UI="Q000150" MajorTopicYN="N">complications</QualifierName><QualifierName UI="Q000523" MajorTopicYN="N">psychology</QualifierName></MeshHeading><MeshHeading><DescriptorName UI="D011446" MajorTopicYN="N">Prospective Studies</DescriptorName></MeshHeading><MeshHeading><DescriptorName UI="D000368" MajorTopicYN="N">Aged</DescriptorName></MeshHeading><MeshHeading><DescriptorName UI="D008875" MajorTopicYN="N">Middle Aged</DescriptorName></MeshHeading><MeshHeading><DescriptorName UI="D011788" MajorTopicYN="Y">Quality of Life</DescriptorName><QualifierName UI="Q000523" MajorTopicYN="N">psychology</QualifierName></MeshHeading><MeshHeading><DescriptorName UI="D003681" MajorTopicYN="N">Dehydration</DescriptorName><QualifierName UI="Q000175" MajorTopicYN="N">diagnosis</QualifierName><QualifierName UI="Q000503" MajorTopicYN="N">physiopathology</QualifierName></MeshHeading><MeshHeading><DescriptorName UI="D000369" MajorTopicYN="N">Aged, 80 and over</DescriptorName></MeshHeading><MeshHeading><DescriptorName UI="D000074267" MajorTopicYN="N">Organism Hydration Status</DescriptorName><QualifierName UI="Q000502" MajorTopicYN="N">physiology</QualifierName></MeshHeading><MeshHeading><DescriptorName UI="D001823" MajorTopicYN="N">Body Composition</DescriptorName><QualifierName UI="Q000502" MajorTopicYN="N">physiology</QualifierName></MeshHeading><MeshHeading><DescriptorName UI="D001834" MajorTopicYN="N">Body Water</DescriptorName></MeshHeading><MeshHeading><DescriptorName UI="D000328" MajorTopicYN="N">Adult</DescriptorName></MeshHeading></MeshHeadingList><KeywordList Owner="NOTNLM"><Keyword MajorTopicYN="N">Bioelectrical impedance analysis</Keyword><Keyword MajorTopicYN="N">Cancer</Keyword><Keyword MajorTopicYN="N">Clinically assisted hydration</Keyword><Keyword MajorTopicYN="N">Dehydration</Keyword><Keyword MajorTopicYN="N">End of life.</Keyword><Keyword MajorTopicYN="N">Hydration</Keyword><Keyword MajorTopicYN="N">Palliative care</Keyword><Keyword MajorTopicYN="N">Renal failure</Keyword><Keyword MajorTopicYN="N">Technology</Keyword></KeywordList><CoiStatement>The authors declare no competing interests.</CoiStatement></MedlineCitation><PubmedData><History><PubMedPubDate PubStatus="received"><Year>2024</Year><Month>3</Month><Day>21</Day></PubMedPubDate><PubMedPubDate PubStatus="accepted"><Year>2024</Year><Month>8</Month><Day>7</Day></PubMedPubDate><PubMedPubDate PubStatus="medline"><Year>2024</Year><Month>8</Month><Day>20</Day><Hour>0</Hour><Minute>43</Minute></PubMedPubDate><PubMedPubDate PubStatus="pubmed"><Year>2024</Year><Month>8</Month><Day>20</Day><Hour>0</Hour><Minute>42</Minute></PubMedPubDate><PubMedPubDate PubStatus="entrez"><Year>2024</Year><Month>8</Month><Day>19</Day><Hour>23</Hour><Minute>37</Minute></PubMedPubDate><PubMedPubDate PubStatus="pmc-release"><Year>2024</Year><Month>8</Month><Day>19</Day></PubMedPubDate></History><PublicationStatus>epublish</PublicationStatus><ArticleIdList><ArticleId IdType="pubmed">39160544</ArticleId><ArticleId IdType="pmc">PMC11331739</ArticleId><ArticleId IdType="doi">10.1186/s12904-024-01542-z</ArticleId><ArticleId IdType="pii">10.1186/s12904-024-01542-z</ArticleId></ArticleIdList><ReferenceList><Reference><Citation>Cerchietti L, Navigante A, Sauri A, Palazzo F. Hypodermoclysis for control of dehydration in terminal-stage cancer. IntJPalliatNurs. 2000;6(8):370&#x2013;4.</Citation><ArticleIdList><ArticleId IdType="pubmed">12411847</ArticleId></ArticleIdList></Reference><Reference><Citation>Nwosu AC, Mayland CR, Mason SR, Khodabukus AF, Varro A, Ellershaw JE. Hydration in advanced cancer: can bioelectrical impedance analysis improve the evidence base? A systematic review of the literature. J Pain Symptom Manage. 2013;46(3):433&#x2013;e466. 10.1016/j.jpainsymman.2012.08.018</Citation><ArticleIdList><ArticleId IdType="doi">10.1016/j.jpainsymman.2012.08.018</ArticleId><ArticleId IdType="pubmed">23200189</ArticleId></ArticleIdList></Reference><Reference><Citation>Good P, Richard R, Syrmis W, Jenkins-Marsh S, Stephens J. Medically assisted hydration for adult palliative care patients. Cochrane Database Syst Rev. 2014;4:CD006273.</Citation><ArticleIdList><ArticleId IdType="pmc">PMC8988261</ArticleId><ArticleId IdType="pubmed">24760678</ArticleId></ArticleIdList></Reference><Reference><Citation>Nwosu AC, Mayland CR, Mason S, Cox TF, Varro A, Ellershaw J. The association of hydration status with physical signs, symptoms and survival in advanced cancer&#x2014;the use of bioelectrical impedance vector analysis (BIVA) technology to evaluate fluid volume in palliative care: an observational study. PLoS ONE. 2016;11(9):e0163114. 10.1371/journal.pone.0163114</Citation><ArticleIdList><ArticleId IdType="doi">10.1371/journal.pone.0163114</ArticleId><ArticleId IdType="pmc">PMC5038956</ArticleId><ArticleId IdType="pubmed">27673684</ArticleId></ArticleIdList></Reference><Reference><Citation>Nwosu AC, Mayland CR, Mason SR, Khodabukus AF, Varro A, Ellershaw JE. Hydration in advanced cancer: can bioelectrical impedance analysis improve the evidence base? A systematic review of the literature. J Pain Symptom Manage. 2013;46(3):433&#x2013;46. e6. 10.1016/j.jpainsymman.2012.08.018</Citation><ArticleIdList><ArticleId IdType="doi">10.1016/j.jpainsymman.2012.08.018</ArticleId><ArticleId IdType="pubmed">23200189</ArticleId></ArticleIdList></Reference><Reference><Citation>Davis MP, Yavuzsen T, Khoshknabi D, Kirkova J, Walsh D, Lasheen W, et al. Bioelectrical impedance phase angle changes during hydration and prognosis in advanced cancer. AmJHospPalliatCare. 2009;26(3):180&#x2013;7.</Citation><ArticleIdList><ArticleId IdType="pubmed">19182217</ArticleId></ArticleIdList></Reference><Reference><Citation>Bennet D, Khorsandian Y, Pelusi J, Mirabella A, Pirrotte P, Zenhausern F. Molecular and physical technologies for monitoring fluid and electrolyte imbalance: a focus on cancer population. Clin Translational Med. 2021;11(6):e461.10.1002/ctm2.461</Citation><ArticleIdList><ArticleId IdType="doi">10.1002/ctm2.461</ArticleId><ArticleId IdType="pmc">PMC8214861</ArticleId><ArticleId IdType="pubmed">34185420</ArticleId></ArticleIdList></Reference><Reference><Citation>Piccoli A, Nigrelli S, Caberlotto A, Bottazzo S, Rossi B, Pillon L, et al. Bivariate normal values of the bioelectrical impedance vector in adult and elderly populations. AmJClinNutr. 1995;61(2):269&#x2013;70.</Citation><ArticleIdList><ArticleId IdType="pubmed">7840061</ArticleId></ArticleIdList></Reference><Reference><Citation>Navigante A, Morgado PC, Casbarien O, Delgado NL, Giglio R, Perman M. Relationship between weakness and phase angle in advanced cancer patients with fatigue. Support Care Cancer. 2013;21(6):1685&#x2013;90. 10.1007/s00520-012-1714-2</Citation><ArticleIdList><ArticleId IdType="doi">10.1007/s00520-012-1714-2</ArticleId><ArticleId IdType="pubmed">23321933</ArticleId></ArticleIdList></Reference><Reference><Citation>Gupta D, Lammersfeld CA, Vashi PG, King J, Dahlk SL, Grutsch JF, et al. Bioelectrical impedance phase angle in clinical practice: implications for prognosis in stage IIIB and IV non-small cell lung cancer. BMCCancer. 2009;9:37.</Citation><ArticleIdList><ArticleId IdType="pmc">PMC2637288</ArticleId><ArticleId IdType="pubmed">19175932</ArticleId></ArticleIdList></Reference><Reference><Citation>Woodrow G, Devine Y, Cullen M, Lindley E. Application of bioelectrical impedance to clinical assessment of body composition in peritoneal dialysis. PeritDialInt. 2007;27(5):496&#x2013;502.</Citation><ArticleIdList><ArticleId IdType="pubmed">17704435</ArticleId></ArticleIdList></Reference><Reference><Citation>Bellizzi V, Scalfi L, Terracciano V, De Nicola L, Minutolo R, Marra M, et al. Early changes in bioelectrical estimates of body composition in chronic kidney disease. J Am Soc Nephrol. 2006;17(5):1481&#x2013;7. 10.1681/ASN.2005070756</Citation><ArticleIdList><ArticleId IdType="doi">10.1681/ASN.2005070756</ArticleId><ArticleId IdType="pubmed">16611719</ArticleId></ArticleIdList></Reference><Reference><Citation>Earthman C, Traughber D, Dobratz J, Howell W. Bioimpedance spectroscopy for clinical assessment of fluid distribution and body cell mass. Nutr Clin Pract. 2007;22(4):389&#x2013;405. 10.1177/0115426507022004389</Citation><ArticleIdList><ArticleId IdType="doi">10.1177/0115426507022004389</ArticleId><ArticleId IdType="pubmed">17644693</ArticleId></ArticleIdList></Reference><Reference><Citation>Piccoli A. Bioelectric impedance measurement for fluid status assessment. ContribNephrol. 2010;164:143&#x2013;52.</Citation><ArticleIdList><ArticleId IdType="pubmed">20428000</ArticleId></ArticleIdList></Reference><Reference><Citation>Thomasset A. Bioelectrical properties of tissue impedance measurements. Lyon Med. 1962;207:12.</Citation><ArticleIdList><ArticleId IdType="pubmed">13920843</ArticleId></ArticleIdList></Reference><Reference><Citation>Hoffer EC, Meador CK, Simpson DC. Correlation of whole-body impedance with total body water volume. J Appl Physiol. 1969;27(4):531&#x2013;4. 10.1152/jappl.1969.27.4.531</Citation><ArticleIdList><ArticleId IdType="doi">10.1152/jappl.1969.27.4.531</ArticleId><ArticleId IdType="pubmed">4898406</ArticleId></ArticleIdList></Reference><Reference><Citation>Kushner RF. Bioelectrical impedance analysis: a review of principles and applications. J Am Coll Nutr. 1992;11(2):199&#x2013;209. 10.1080/07315724.1992.12098245</Citation><ArticleIdList><ArticleId IdType="doi">10.1080/07315724.1992.12098245</ArticleId><ArticleId IdType="pubmed">1578098</ArticleId></ArticleIdList></Reference><Reference><Citation>Kushner RF, Schoeller DA, Fjeld CR, Danford L. Is the impedance index (ht2/R) significant in predicting total body water? Am J Clin Nutr. 1992;56(5):835&#x2013;9. 10.1093/ajcn/56.5.835</Citation><ArticleIdList><ArticleId IdType="doi">10.1093/ajcn/56.5.835</ArticleId><ArticleId IdType="pubmed">1415001</ArticleId></ArticleIdList></Reference><Reference><Citation>Deurenberg P, van der Kooy K, Leenen R, Weststrate JA, Seidell JC. Sex and age specific prediction formulas for estimating body composition from bioelectrical impedance: a cross-validation study. Int J Obes. 1991;15(1):17&#x2013;25.</Citation><ArticleIdList><ArticleId IdType="pubmed">2010255</ArticleId></ArticleIdList></Reference><Reference><Citation>Kushner RF, Schoeller DA. Estimation of total body water by bioelectrical impedance analysis. Am J Clin Nutr. 1986;44(3):417&#x2013;24. 10.1093/ajcn/44.3.417</Citation><ArticleIdList><ArticleId IdType="doi">10.1093/ajcn/44.3.417</ArticleId><ArticleId IdType="pubmed">3529918</ArticleId></ArticleIdList></Reference><Reference><Citation>Davies PS, Preece MA, Hicks CJ, Halliday D. The prediction of total body water using bioelectrical impedance in children and adolescents. Ann Hum Biol. 1988;15(3):237&#x2013;40. 10.1080/03014468800009681</Citation><ArticleIdList><ArticleId IdType="doi">10.1080/03014468800009681</ArticleId><ArticleId IdType="pubmed">3389733</ArticleId></ArticleIdList></Reference><Reference><Citation>Deurenberg P, van der Kooij K, Evers P, Hulshof T. Assessment of body composition by bioelectrical impedance in a population aged greater than 60 y. Am J Clin Nutr. 1990;51(1):3&#x2013;6. 10.1093/ajcn/51.1.3</Citation><ArticleIdList><ArticleId IdType="doi">10.1093/ajcn/51.1.3</ArticleId><ArticleId IdType="pubmed">2296928</ArticleId></ArticleIdList></Reference><Reference><Citation>Van Loan M, Mayclin P. Bioelectrical impedance analysis: is it a reliable estimator of lean body mass and total body water. Hum Biol. 1987;59(2):299&#x2013;309.</Citation><ArticleIdList><ArticleId IdType="pubmed">3596569</ArticleId></ArticleIdList></Reference><Reference><Citation>Jackson AS, Pollock ML, Graves JE, Mahar MT. Reliability and validity of bioelectrical impedance in determining body composition. Journal of applied physiology (Bethesda, Md: 1985). 1988;64(2):529&#x2009;&#x2013;&#x2009;34.</Citation><ArticleIdList><ArticleId IdType="pubmed">3372410</ArticleId></ArticleIdList></Reference><Reference><Citation>Nyboer J. Electrical impedance plethysmography. Oxford: Blackwell Scientific Publications Ltd. Springfield, Illinois: Charles C.Thomas.;; 1959.</Citation></Reference><Reference><Citation>Simons JP, Schols AM, Westerterp KR, Ten Velde GP, Wouters EF. Bioelectrical impedance analysis to assess changes in total body water in patients with cancer. Clin Nutr. 1999;18(1):35&#x2013;9. 10.1016/S0261-5614(99)80047-8</Citation><ArticleIdList><ArticleId IdType="doi">10.1016/S0261-5614(99)80047-8</ArticleId><ArticleId IdType="pubmed">10459080</ArticleId></ArticleIdList></Reference><Reference><Citation>Kyle UG, Bosaeus I, De Lorenzo AD, Deurenberg P, Elia M, Gomez JM, et al. Bioelectrical impedance analysis&#x2013;part I: review of principles and methods. ClinNutr. 2004;23(5):1226&#x2013;43.</Citation><ArticleIdList><ArticleId IdType="pubmed">15380917</ArticleId></ArticleIdList></Reference><Reference><Citation>Campa F, Toselli S, Mazzilli M, Gobbo LA, Coratella G. Assessment of body composition in athletes: a narrative review of available methods with special reference to quantitative and qualitative bioimpedance analysis. Nutrients. 2021;13(5):1620. 10.3390/nu13051620</Citation><ArticleIdList><ArticleId IdType="doi">10.3390/nu13051620</ArticleId><ArticleId IdType="pmc">PMC8150618</ArticleId><ArticleId IdType="pubmed">34065984</ArticleId></ArticleIdList></Reference><Reference><Citation>McDonald JJ, Chanduvi B, Velarde G, Cama R, Diaz F, Carrillo L, et al. Bioimpedance monitoring of rehydration in cholera. Lancet. 1993;341(8852):1049&#x2013;51. 10.1016/0140-6736(93)92410-U</Citation><ArticleIdList><ArticleId IdType="doi">10.1016/0140-6736(93)92410-U</ArticleId><ArticleId IdType="pubmed">8096957</ArticleId></ArticleIdList></Reference><Reference><Citation>Bozzetto S, Piccoli A, Montini G. Bioelectrical impedance vector analysis to evaluate relative hydration status. PediatrNephrol. 2009.</Citation><ArticleIdList><ArticleId IdType="pubmed">19876654</ArticleId></ArticleIdList></Reference><Reference><Citation>Codognotto M, Piazza M, Frigatti P, Piccoli A. Influence of localized edema on whole-body and segmental bioelectrical impedance. Nutrition. 2008;24(6):569&#x2013;74. 10.1016/j.nut.2008.02.009</Citation><ArticleIdList><ArticleId IdType="doi">10.1016/j.nut.2008.02.009</ArticleId><ArticleId IdType="pubmed">18455657</ArticleId></ArticleIdList></Reference><Reference><Citation>Nescolarde L, Piccoli A, Roman A, Nunez A, Morales R, Tamayo J, et al. Bioelectrical impedance vector analysis in haemodialysis patients: relation between oedema and mortality. Physiol Meas. 2004;25(5):1271&#x2013;80. 10.1088/0967-3334/25/5/016</Citation><ArticleIdList><ArticleId IdType="doi">10.1088/0967-3334/25/5/016</ArticleId><ArticleId IdType="pubmed">15535191</ArticleId></ArticleIdList></Reference><Reference><Citation>Piccoli A. Bioelectric impedance vector distribution in peritoneal dialysis patients with different hydration status. Kidney Int. 2004;65(3):1050&#x2013;63. 10.1111/j.1523-1755.2004.00467.x</Citation><ArticleIdList><ArticleId IdType="doi">10.1111/j.1523-1755.2004.00467.x</ArticleId><ArticleId IdType="pubmed">14871426</ArticleId></ArticleIdList></Reference><Reference><Citation>Pillon L, Piccoli A, Lowrie EG, Lazarus JM, Chertow GM. Vector length as a proxy for the adequacy of ultrafiltration in hemodialysis. Kidney Int. 2004;66(3):1266&#x2013;71. 10.1111/j.1523-1755.2004.00881.x</Citation><ArticleIdList><ArticleId IdType="doi">10.1111/j.1523-1755.2004.00881.x</ArticleId><ArticleId IdType="pubmed">15327426</ArticleId></ArticleIdList></Reference><Reference><Citation>Toso S, Piccoli A, Gusella M, Menon D, Crepaldi G, Bononi A, et al. Bioimpedance vector pattern in cancer patients without disease versus locally advanced or disseminated disease. Nutrition. 2003;19(6):510&#x2013;4. 10.1016/S0899-9007(02)01084-5</Citation><ArticleIdList><ArticleId IdType="doi">10.1016/S0899-9007(02)01084-5</ArticleId><ArticleId IdType="pubmed">12781850</ArticleId></ArticleIdList></Reference><Reference><Citation>Nwosu AC, Morris L, Mayland C, Mason S, Pettitt A, Ellershaw J. Longitudinal bioimpedance assessments to evaluate hydration in POEMS syndrome. BMJ Support Palliat Care. 2016.</Citation><ArticleIdList><ArticleId IdType="pmc">PMC5013159</ArticleId><ArticleId IdType="pubmed">27125269</ArticleId></ArticleIdList></Reference><Reference><Citation>Toso S, Piccoli A, Gusella M, Menon D, Bononi A, Crepaldi G, et al. Altered tissue electric properties in lung cancer patients as detected by bioelectric impedance vector analysis. Nutrition. 2000;16(2):120&#x2013;4. 10.1016/S0899-9007(99)00230-0</Citation><ArticleIdList><ArticleId IdType="doi">10.1016/S0899-9007(99)00230-0</ArticleId><ArticleId IdType="pubmed">10696635</ArticleId></ArticleIdList></Reference><Reference><Citation>Malecka-Massalska T, Smolen A, Zubrzycki J, Lupa-Zatwarnicka K, Morshed K. Bioimpedance vector pattern in head and neck squamous cell carcinoma. JPhysiol Pharmacol. 2012;63(1):101&#x2013;4.</Citation><ArticleIdList><ArticleId IdType="pubmed">22460467</ArticleId></ArticleIdList></Reference><Reference><Citation>Nwosu AC, Mayland CR, Mason S, Cox TF, Varro A, Stanley S, et al. Bioelectrical impedance vector analysis (BIVA) as a method to compare body composition differences according to cancer stage and type. Clin Nutr ESPEN. 2019;30:59&#x2013;66. 10.1016/j.clnesp.2019.02.006</Citation><ArticleIdList><ArticleId IdType="doi">10.1016/j.clnesp.2019.02.006</ArticleId><ArticleId IdType="pubmed">30904230</ArticleId></ArticleIdList></Reference><Reference><Citation>Parkash R, Burge F. The family&#x2019;s perspective on issues of hydration in terminal care. JPalliatCare. 1997;13(4):23&#x2013;7.</Citation><ArticleIdList><ArticleId IdType="pubmed">9447808</ArticleId></ArticleIdList></Reference><Reference><Citation>Palliative and end of life care Priority Setting Partnership (PeolcPSP). James Lind Alliance; 2015 January.</Citation></Reference><Reference><Citation>Digital NHS. Ethnicity. 2023.</Citation></Reference><Reference><Citation>Marie Curie Hospice Liverpool. Hospice minimum dataset for 2012. 2013.</Citation></Reference><Reference><Citation>Lukaski HC, Bolonchuk WW, Hall CB, Siders WA. Validation of tetrapolar bioelectrical impedance method to assess human body composition. J Appl Physiol. 1986;60(4):1327&#x2013;32. 10.1152/jappl.1986.60.4.1327</Citation><ArticleIdList><ArticleId IdType="doi">10.1152/jappl.1986.60.4.1327</ArticleId><ArticleId IdType="pubmed">3700310</ArticleId></ArticleIdList></Reference><Reference><Citation>Kyle UG, Bosaeus I, De Lorenzo AD, Deurenberg P, Elia M, Manuel GJ, et al. Bioelectrical impedance analysis-part II: utilization in clinical practice. ClinNutr. 2004;23(6):1430&#x2013;53.</Citation><ArticleIdList><ArticleId IdType="pubmed">15556267</ArticleId></ArticleIdList></Reference><Reference><Citation>Burge F. Dehydration symptoms of palliative care cancer patients. McGill University, Montreal; 1991.</Citation><ArticleIdList><ArticleId IdType="pubmed">7525778</ArticleId></ArticleIdList></Reference><Reference><Citation>Burge FI. Dehydration symptoms of palliative care cancer patients. JPain SymptomManage. 1993;8(7):454&#x2013;64.</Citation><ArticleIdList><ArticleId IdType="pubmed">7525778</ArticleId></ArticleIdList></Reference><Reference><Citation>O&#x2019;Connor B, Jeter K, Blackwell S, Burke L, Conway EV, Moran C, et al. Cancer symptom scale preference: one size to fit all? ASCO Meeting Abstracts. 2015;33(29suppl):69.</Citation></Reference><Reference><Citation>Bruera E, Kuehn N, Miller MJ, Selmser P, Macmillan K. The Edmonton Symptom Assessment System (ESAS): a simple method for the assessment of palliative care patients. J Palliat Care. 1991;7(2):6&#x2013;9. 10.1177/082585979100700202</Citation><ArticleIdList><ArticleId IdType="doi">10.1177/082585979100700202</ArticleId><ArticleId IdType="pubmed">1714502</ArticleId></ArticleIdList></Reference><Reference><Citation>Chang VT, Hwang SS, Feuerman M. Validation of the Edmonton Symptom Assessment Scale. Cancer. 2000;88(9):2164&#x2013;71. 10.1002/(SICI)1097-0142(20000501)88:9&lt;2164::AID-CNCR24&gt;3.0.CO;2-5</Citation><ArticleIdList><ArticleId IdType="doi">10.1002/(SICI)1097-0142(20000501)88:9&lt;2164::AID-CNCR24&gt;3.0.CO;2-5</ArticleId><ArticleId IdType="pubmed">10813730</ArticleId></ArticleIdList></Reference><Reference><Citation>Morita T, Hyodo I, Yoshimi T, Ikenaga M, Tamura Y, Yoshizawa A, et al. Association between hydration volume and symptoms in terminally ill cancer patients with abdominal malignancies. AnnOncol. 2005;16(4):640&#x2013;7.</Citation><ArticleIdList><ArticleId IdType="pubmed">15684225</ArticleId></ArticleIdList></Reference><Reference><Citation>Gross CR, Lindquist RD, Woolley AC, Granieri R, Allard K, Webster B. Clinical indicators of dehydration severity in elderly patients. JEmergMed. 1992;10(3):267&#x2013;74.</Citation><ArticleIdList><ArticleId IdType="pubmed">1624737</ArticleId></ArticleIdList></Reference><Reference><Citation>Eaton D, Bannister P, Mulley GP, Connolly MJ. Axillary sweating in clinical assessment of dehydration in ill elderly patients. BMJ. 1994;308(6939):1271. 10.1136/bmj.308.6939.1271</Citation><ArticleIdList><ArticleId IdType="doi">10.1136/bmj.308.6939.1271</ArticleId><ArticleId IdType="pmc">PMC2540218</ArticleId><ArticleId IdType="pubmed">8205020</ArticleId></ArticleIdList></Reference><Reference><Citation>McGee S, Abernethy WB III, Simel DL. The rational clinical examination. Is this Patient Hypovolemic? JAMA. 1999;281(11):1022&#x2013;9.</Citation><ArticleIdList><ArticleId IdType="pubmed">10086438</ArticleId></ArticleIdList></Reference><Reference><Citation>Bruera E, Hui D, Dalal S, Torres-Vigil I, Trumble J, Roosth J, et al. Parenteral hydration in patients with advanced cancer: a multicenter, double-blind, placebo-controlled randomized trial. J Clin Oncol. 2013;31(1):111&#x2013;8. 10.1200/JCO.2012.44.6518</Citation><ArticleIdList><ArticleId IdType="doi">10.1200/JCO.2012.44.6518</ArticleId><ArticleId IdType="pmc">PMC3530688</ArticleId><ArticleId IdType="pubmed">23169523</ArticleId></ArticleIdList></Reference><Reference><Citation>Nakajima N. A clinical study on the influence of hydration volume toward symptoms in terminally ill cancer patients with abdomincal malignancies. 2012. p. 462-.</Citation></Reference><Reference><Citation>Cella DF, Tulsky DS, Gray G, Sarafian B, Linn E, Bonomi A, et al. The Functional Assessment of Cancer Therapy scale: development and validation of the general measure. J Clin Oncol. 1993;11(3):570&#x2013;9. 10.1200/JCO.1993.11.3.570</Citation><ArticleIdList><ArticleId IdType="doi">10.1200/JCO.1993.11.3.570</ArticleId><ArticleId IdType="pubmed">8445433</ArticleId></ArticleIdList></Reference><Reference><Citation>Mah K, Swami N, Le LW, Chow R, Hannon BL, Rodin G, et al. Validation of the 7-item Functional Assessment of Cancer Therapy&#x2010;General (FACT&#x2010;G7) as a short measure of quality of life in patients with advanced cancer. Cancer. 2020;126(16):3750&#x2013;7. 10.1002/cncr.32981</Citation><ArticleIdList><ArticleId IdType="doi">10.1002/cncr.32981</ArticleId><ArticleId IdType="pubmed">32459377</ArticleId></ArticleIdList></Reference><Reference><Citation>Oken MM, Creech RH, Tormey DC, Horton J, Davis TE, McFadden ET, et al. Toxicity and response criteria of the Eastern Cooperative Oncology Group. Am J Clin Oncol. 1982;5(6):649&#x2013;55. 10.1097/00000421-198212000-00014</Citation><ArticleIdList><ArticleId IdType="doi">10.1097/00000421-198212000-00014</ArticleId><ArticleId IdType="pubmed">7165009</ArticleId></ArticleIdList></Reference><Reference><Citation>Jang RW, Caraiscos VB, Swami N, Banerjee S, Mak E, Kaya E, et al. Simple prognostic model for patients with advanced cancer based on performance status. J Oncol Pract. 2014;10(5):e335&#x2013;41. 10.1200/JOP.2014.001457</Citation><ArticleIdList><ArticleId IdType="doi">10.1200/JOP.2014.001457</ArticleId><ArticleId IdType="pubmed">25118208</ArticleId></ArticleIdList></Reference><Reference><Citation>Frucht SJ, Leurgans SE, Hallett M, Fahn S. The Unified Myoclonus Rating Scale. Adv Neurol. 2002;89:361&#x2013;76.</Citation><ArticleIdList><ArticleId IdType="pubmed">11968461</ArticleId></ArticleIdList></Reference><Reference><Citation>Leadership Alliance for the Care of Dying People. One chance to get it right. 2014.</Citation></Reference><Reference><Citation>Health NIf, Excellence C. End of life care for adults: service delivery. National Institute for Health and Care Excellence; 2019.</Citation><ArticleIdList><ArticleId IdType="pubmed">31633897</ArticleId></ArticleIdList></Reference><Reference><Citation>Rolls BJ, Phillips PA. Aging and disturbances of thirst and fluid balance. Nutr Rev. 1990;48(3):137&#x2013;44. 10.1111/j.1753-4887.1990.tb02915.x</Citation><ArticleIdList><ArticleId IdType="doi">10.1111/j.1753-4887.1990.tb02915.x</ArticleId><ArticleId IdType="pubmed">2406645</ArticleId></ArticleIdList></Reference><Reference><Citation>Kenney WL, Chiu P. Influence of age on thirst and fluid intake. Med Sci Sports Exerc. 2001;33(9):1524&#x2013;32. 10.1097/00005768-200109000-00016</Citation><ArticleIdList><ArticleId IdType="doi">10.1097/00005768-200109000-00016</ArticleId><ArticleId IdType="pubmed">11528342</ArticleId></ArticleIdList></Reference><Reference><Citation>Ritz P, Vol S, Berrut G, Tack I, Arnaud MJ, Tichet J. Influence of gender and body composition on hydration and body water spaces. Clin Nutr. 2008;27(5):740&#x2013;6. 10.1016/j.clnu.2008.07.010</Citation><ArticleIdList><ArticleId IdType="doi">10.1016/j.clnu.2008.07.010</ArticleId><ArticleId IdType="pubmed">18774628</ArticleId></ArticleIdList></Reference><Reference><Citation>Davies AN, Waghorn M, Webber K, Johnsen S, Mendis J, Boyle J. A cluster randomised feasibility trial of clinically assisted hydration in cancer patients in the last days of life. Palliat Med. 2018;32(4):733&#x2013;43. 10.1177/0269216317741572</Citation><ArticleIdList><ArticleId IdType="doi">10.1177/0269216317741572</ArticleId><ArticleId IdType="pubmed">29343167</ArticleId></ArticleIdList></Reference><Reference><Citation>Nakajima N, Hata Y, Kusumuto K. A clinical study on the influence of hydration volume on the signs of terminally ill cancer patients with abdominal malignancies. J Palliat Med. 2013;16(2):185&#x2013;9. 10.1089/jpm.2012.0233</Citation><ArticleIdList><ArticleId IdType="doi">10.1089/jpm.2012.0233</ArticleId><ArticleId IdType="pubmed">23327196</ArticleId></ArticleIdList></Reference><Reference><Citation>Morita T, Shima Y, Miyashita M, Kimura R, Adachi I. Physician- and nurse-reported effects of intravenous hydration therapy on symptoms of terminally ill patients with cancer. JPalliatMed. 2004;7(5):683&#x2013;93.</Citation><ArticleIdList><ArticleId IdType="pubmed">15588360</ArticleId></ArticleIdList></Reference><Reference><Citation>Fritzson A, Tavelin B, Axelsson B. Association between parenteral fluids and symptoms in hospital end-of-life care: an observational study of 280 patients. BMJ Support Palliat Care. 2013.</Citation><ArticleIdList><ArticleId IdType="pubmed">24644196</ArticleId></ArticleIdList></Reference><Reference><Citation>Piccoli A. Pastori, G. BIVA software2002.</Citation></Reference><Reference><Citation>Gatignon H. Multivariate normal distribution. Statistical analysis of management data. Springer; 2011. pp. 9&#x2013;28.</Citation></Reference><Reference><Citation>Piccoli A, Rossi B, Pillon L, Bucciante G. A new method for monitoring body fluid variation by bioimpedance analysis: the RXc graph. Kidney Int. 1994;46(2):534&#x2013;9. 10.1038/ki.1994.305</Citation><ArticleIdList><ArticleId IdType="doi">10.1038/ki.1994.305</ArticleId><ArticleId IdType="pubmed">7967368</ArticleId></ArticleIdList></Reference><Reference><Citation>Piccoli A, Brunani A, Savia G, Pillon L, Favaro E, Berselli ME, et al. Discriminating between body fat and fluid changes in the obese adult using bioimpedance vector analysis. IntJObesRelat Metab Disord. 1998;22(2):97&#x2013;104.10.1038/sj.ijo.0800551</Citation><ArticleIdList><ArticleId IdType="doi">10.1038/sj.ijo.0800551</ArticleId><ArticleId IdType="pubmed">9504317</ArticleId></ArticleIdList></Reference><Reference><Citation>Piccoli A, Pillon L, Dumler F. Impedance vector distribution by sex, race, body mass index, and age in the United States: standard reference intervals as bivariate Z scores. Nutrition. 2002;18(2):153&#x2013;67. 10.1016/S0899-9007(01)00665-7</Citation><ArticleIdList><ArticleId IdType="doi">10.1016/S0899-9007(01)00665-7</ArticleId><ArticleId IdType="pubmed">11844647</ArticleId></ArticleIdList></Reference><Reference><Citation>Lentner C. Introduction to statistics. Statistical tables. Mathematical formulae. Geigy scientific Table 8 ed. Basel: Ciba-Geigy Limited; 1982. p. 1.</Citation></Reference><Reference><Citation>R&#xf6;sler A, Lehmann F, Krause T, Wirth R, von Renteln-Kruse W. Nutritional and hydration status in elderly subjects: clinical rating versus bioimpedance analysis. Arch Gerontol Geriatr. 2010;50(3):e81&#x2013;5. 10.1016/j.archger.2009.06.007</Citation><ArticleIdList><ArticleId IdType="doi">10.1016/j.archger.2009.06.007</ArticleId><ArticleId IdType="pubmed">19616321</ArticleId></ArticleIdList></Reference><Reference><Citation>Hutcheson GD, Sofroniou N. The Multivariate Social Scientist: introductory statistics using generalized Linear models. SAGE; 1999.</Citation></Reference><Reference><Citation>Velicer WF, Fava JL. Affects of variable and subject sampling on factor pattern recovery. Psychol Methods. 1998;3(2):231.10.1037/1082-989X.3.2.231</Citation><ArticleIdList><ArticleId IdType="doi">10.1037/1082-989X.3.2.231</ArticleId></ArticleIdList></Reference><Reference><Citation>Armitage P, Berry G, Matthews JNS. Statistical methods in Medical Research. Wiley; 2008.</Citation></Reference><Reference><Citation>Sarhill N, Walsh D, Nelson K, Davis M. Evaluation and treatment of cancer-related fluid deficits: volume depletion and dehydration. SupportCare Cancer. 2001;9(6):408&#x2013;19.10.1007/s005200100251</Citation><ArticleIdList><ArticleId IdType="doi">10.1007/s005200100251</ArticleId><ArticleId IdType="pubmed">11585267</ArticleId></ArticleIdList></Reference><Reference><Citation>Sarhill N, Mahmoud FA, Christie R, Tahir A. Assessment of nutritional status and fluid deficits in advanced cancer. AmJHospPalliatCare. 2003;20(6):465&#x2013;73.</Citation><ArticleIdList><ArticleId IdType="pubmed">14649565</ArticleId></ArticleIdList></Reference><Reference><Citation>Martinoli R, Mohamed EI, Maiolo C, Cianci R, Denoth F, Salvadori S, et al. Total body water estimation using bioelectrical impedance: a meta-analysis of the data available in the literature. Acta Diabetol. 2003;40(Suppl 1):S203&#x2013;6. 10.1007/s00592-003-0066-2</Citation><ArticleIdList><ArticleId IdType="doi">10.1007/s00592-003-0066-2</ArticleId><ArticleId IdType="pubmed">14618473</ArticleId></ArticleIdList></Reference><Reference><Citation>McKiernan F, Houchins JA, Mattes RD. Relationships between human thirst, hunger, drinking, and feeding. Physiol Behav. 2008;94(5):700&#x2013;8. 10.1016/j.physbeh.2008.04.007</Citation><ArticleIdList><ArticleId IdType="doi">10.1016/j.physbeh.2008.04.007</ArticleId><ArticleId IdType="pmc">PMC2467458</ArticleId><ArticleId IdType="pubmed">18499200</ArticleId></ArticleIdList></Reference><Reference><Citation>Raijmakers NJ, van Costantini ZL, Caraceni M, Clark A, Lundquist J. Artificial nutrition and hydration in the last week of life in cancer patients. Syst Literature Rev Practices Eff AnnOncol. 2011;22(7):1478&#x2013;86.</Citation><ArticleIdList><ArticleId IdType="pubmed">21199887</ArticleId></ArticleIdList></Reference><Reference><Citation>Mietlicki EG, Nowak EL, Daniels D. The effect of ghrelin on water intake during dipsogenic conditions. Physiol Behav. 2009;96(1):37&#x2013;43. 10.1016/j.physbeh.2008.08.004</Citation><ArticleIdList><ArticleId IdType="doi">10.1016/j.physbeh.2008.08.004</ArticleId><ArticleId IdType="pmc">PMC2635884</ArticleId><ArticleId IdType="pubmed">18761029</ArticleId></ArticleIdList></Reference><Reference><Citation>Haghighatdoost F, Feizi A, Esmaillzadeh A, Rashidi-Pourfard N, Keshteli AH, Roohafza H, et al. Drinking plain water is associated with decreased risk of depression and anxiety in adults: results from a large cross-sectional study. World J Psychiatry. 2018;8(3):88. 10.5498/wjp.v8.i3.88</Citation><ArticleIdList><ArticleId IdType="doi">10.5498/wjp.v8.i3.88</ArticleId><ArticleId IdType="pmc">PMC6147771</ArticleId><ArticleId IdType="pubmed">30254979</ArticleId></ArticleIdList></Reference><Reference><Citation>Smith JA, Pati D, Wang L, de Kloet AD, Frazier CJ, Krause EG. Hydration and beyond: neuropeptides as mediators of hydromineral balance, anxiety and stress-responsiveness. Front Syst Neurosci. 2015;9:46. 10.3389/fnsys.2015.00046</Citation><ArticleIdList><ArticleId IdType="doi">10.3389/fnsys.2015.00046</ArticleId><ArticleId IdType="pmc">PMC4379895</ArticleId><ArticleId IdType="pubmed">25873866</ArticleId></ArticleIdList></Reference><Reference><Citation>Del Rio M, Shand B, Bonati P, Palma A, Maldonado A, Taboada P, et al. Hydration and nutrition at the end of life: a systematic review of emotional impact, perceptions, and decision-making among patients, family, and health care staff. Psycho&#x2010;Oncology. 2012;21(9):913&#x2013;21. 10.1002/pon.2099</Citation><ArticleIdList><ArticleId IdType="doi">10.1002/pon.2099</ArticleId><ArticleId IdType="pubmed">22162174</ArticleId></ArticleIdList></Reference><Reference><Citation>Baillie J, Anagnostou D, Sivell S, Van Godwin J, Byrne A, Nelson A. Symptom management, nutrition and hydration at end-of-life: a qualitative exploration of patients&#x2019;, carers&#x2019; and health professionals&#x2019; experiences and further research questions. BMC Palliat Care. 2018;17:1&#x2013;13.10.1186/s12904-018-0314-4</Citation><ArticleIdList><ArticleId IdType="doi">10.1186/s12904-018-0314-4</ArticleId><ArticleId IdType="pmc">PMC5901670</ArticleId><ArticleId IdType="pubmed">29656713</ArticleId></ArticleIdList></Reference><Reference><Citation>Guo D, Lin T, Deng C, Zheng Y, Gao L, Yue J. Risk factors for delirium in the palliative care population: a systematic review and meta-analysis. Front Psychiatry. 2021;12:772387. 10.3389/fpsyt.2021.772387</Citation><ArticleIdList><ArticleId IdType="doi">10.3389/fpsyt.2021.772387</ArticleId><ArticleId IdType="pmc">PMC8566675</ArticleId><ArticleId IdType="pubmed">34744847</ArticleId></ArticleIdList></Reference><Reference><Citation>Lawlor PG. Delirium and dehydration: some fluid for thought? SupportCare Cancer. 2002;10(6):445&#x2013;54.10.1007/s00520-001-0334-z</Citation><ArticleIdList><ArticleId IdType="doi">10.1007/s00520-001-0334-z</ArticleId><ArticleId IdType="pubmed">12353122</ArticleId></ArticleIdList></Reference><Reference><Citation>Currow DC, Higginson IJ, Johnson MJ. Breathlessness&#x2013;current and emerging mechanisms, measurement and management: a discussion from an European Association of Palliative Care workshop. Palliat Med. 2013;27(10):932&#x2013;8. 10.1177/0269216313493819</Citation><ArticleIdList><ArticleId IdType="doi">10.1177/0269216313493819</ArticleId><ArticleId IdType="pubmed">23838379</ArticleId></ArticleIdList></Reference><Reference><Citation>Fabbro ED, Dalal S, Bruera E. Symptom control in palliative care&#x2014;part III: Dyspnea and delirium. J Palliat Med. 2006;9(2):422&#x2013;36. 10.1089/jpm.2006.9.422</Citation><ArticleIdList><ArticleId IdType="doi">10.1089/jpm.2006.9.422</ArticleId><ArticleId IdType="pubmed">16629572</ArticleId></ArticleIdList></Reference><Reference><Citation>Waller A, Hershkowitz M, Adunsky A. The effect of intravenous fluid infusion on blood and urine parameters of hydration and on state of consciousness in terminal cancer patients. AmJHospPalliatCare. 1994;11(6):22&#x2013;7.</Citation><ArticleIdList><ArticleId IdType="pubmed">7893564</ArticleId></ArticleIdList></Reference><Reference><Citation>Gwilliam B, Keeley V, Todd C, Roberts C, Gittins M, Kelly L, et al. Prognosticating in patients with advanced cancer&#x2013;observational study comparing the accuracy of clinicians&#x2019; and patients&#x2019; estimates of survival. Ann Oncol. 2013;24(2):482&#x2013;8. 10.1093/annonc/mds341</Citation><ArticleIdList><ArticleId IdType="doi">10.1093/annonc/mds341</ArticleId><ArticleId IdType="pubmed">23028038</ArticleId></ArticleIdList></Reference><Reference><Citation>Piccoli A. Identification of operational clues to dry weight prescription in hemodialysis using bioimpedance vector analysis. The Italian Hemodialysis-Bioelectrical Impedance Analysis (HD-BIA) Study Group. Kidney Int. 1998;53(4):1036&#x2013;43. 10.1111/j.1523-1755.1998.00843.x</Citation><ArticleIdList><ArticleId IdType="doi">10.1111/j.1523-1755.1998.00843.x</ArticleId><ArticleId IdType="pubmed">9551415</ArticleId></ArticleIdList></Reference><Reference><Citation>Piccoli A, Rossi B, Pillon L, Bucciante G. Body fluid overload and bioelectrical impedance analysis in renal patients. Miner Electrolyte Metab. 1996;22(1&#x2013;3):76&#x2013;8.</Citation><ArticleIdList><ArticleId IdType="pubmed">8676831</ArticleId></ArticleIdList></Reference><Reference><Citation>Guglielmi FW, Mastronuzzi T, Pietrini L, Panarese A, Panella C, Francavilla A. The RXc graph in evaluating and monitoring fluid balance in patients with liver cirrhosis. Ann N Y Acad Sci. 1999;873:105&#x2013;11. 10.1111/j.1749-6632.1999.tb09456.x</Citation><ArticleIdList><ArticleId IdType="doi">10.1111/j.1749-6632.1999.tb09456.x</ArticleId><ArticleId IdType="pubmed">10372157</ArticleId></ArticleIdList></Reference><Reference><Citation>Chung M, Kozuch P. Treatment of malignant ascites. Curr Treat Options Oncol. 2008;9(2&#x2013;3):215&#x2013;33. 10.1007/s11864-008-0068-y</Citation><ArticleIdList><ArticleId IdType="doi">10.1007/s11864-008-0068-y</ArticleId><ArticleId IdType="pubmed">18777213</ArticleId></ArticleIdList></Reference><Reference><Citation>Froudarakis ME. Pleural effusion in lung cancer: more questions than answers. Respir Int Rev Thorac Dis. 2012;83(5):367&#x2013;76.</Citation><ArticleIdList><ArticleId IdType="pubmed">22584211</ArticleId></ArticleIdList></Reference><Reference><Citation>Ferrell B, Koczywas M, Grannis F, Harrington A. Palliative care in lung cancer. Surg Clin North Am. 2011;91(2):403&#x2013;17. ix. 10.1016/j.suc.2010.12.003</Citation><ArticleIdList><ArticleId IdType="doi">10.1016/j.suc.2010.12.003</ArticleId><ArticleId IdType="pmc">PMC3655433</ArticleId><ArticleId IdType="pubmed">21419260</ArticleId></ArticleIdList></Reference><Reference><Citation>O&#x2019;Toole J, Jammallo LS, Skolny MN, Miller CL, Elliott K, Specht MC, et al. Lymphedema following treatment for breast cancer: a new approach to an old problem. Crit Rev Oncol/Hematol. 2013;88(2):437&#x2013;46. 10.1016/j.critrevonc.2013.05.001</Citation><ArticleIdList><ArticleId IdType="doi">10.1016/j.critrevonc.2013.05.001</ArticleId><ArticleId IdType="pmc">PMC3784614</ArticleId><ArticleId IdType="pubmed">23777977</ArticleId></ArticleIdList></Reference><Reference><Citation>Prinsen CA, Vohra S, Rose MR, King-Jones S, Ishaque S, Bhaloo Z, et al. Core outcome measures in effectiveness trials (COMET) initiative: protocol for an international Delphi study to achieve consensus on how to select outcome measurement instruments for outcomes included in a &#x2018;core outcome set&#x2019;. Trials. 2014;15(1):1&#x2013;7. 10.1186/1745-6215-15-247</Citation><ArticleIdList><ArticleId IdType="doi">10.1186/1745-6215-15-247</ArticleId><ArticleId IdType="pmc">PMC4082295</ArticleId><ArticleId IdType="pubmed">24962012</ArticleId></ArticleIdList></Reference><Reference><Citation>Padhi S, Bullock I, Li L, Stroud M. Intravenous fluid therapy for adults in hospital: summary of NICE guidance. BMJ. 2013;347.</Citation><ArticleIdList><ArticleId IdType="pubmed">24326887</ArticleId></ArticleIdList></Reference><Reference><Citation>Yalin SF, Gulcicek S, Avci S, Erkalma Senates B, Altiparmak MR, Trabulus S, et al. Single-frequency and multi&#x2010;frequency bioimpedance analysis: what is the difference? Nephrology. 2018;23(5):438&#x2013;45. 10.1111/nep.13042</Citation><ArticleIdList><ArticleId IdType="doi">10.1111/nep.13042</ArticleId><ArticleId IdType="pubmed">28295857</ArticleId></ArticleIdList></Reference><Reference><Citation>Villa F, Magnani A, Maggioni MA, Stahn A, Rampichini S, Merati G, et al. Wearable multi-frequency and multi-segment bioelectrical impedance spectroscopy for unobtrusively tracking body fluid shifts during physical activity in real-field applications: a preliminary study. Sensors. 2016;16(5):673. 10.3390/s16050673</Citation><ArticleIdList><ArticleId IdType="doi">10.3390/s16050673</ArticleId><ArticleId IdType="pmc">PMC4883364</ArticleId><ArticleId IdType="pubmed">27187389</ArticleId></ArticleIdList></Reference><Reference><Citation>Bundred NJ, Stockton C, Keeley V, Riches K, Ashcroft L, Evans A, et al. Comparison of multi-frequency bioimpedance with perometry for the early detection and intervention of lymphoedema after axillary node clearance for breast cancer. Breast Cancer Res Treat. 2015;151:121&#x2013;9. 10.1007/s10549-015-3357-8</Citation><ArticleIdList><ArticleId IdType="doi">10.1007/s10549-015-3357-8</ArticleId><ArticleId IdType="pubmed">25850535</ArticleId></ArticleIdList></Reference><Reference><Citation>Czerniec SA, Ward LC, Lee M-J, Refshauge KM, Beith J, Kilbreath SL. Segmental measurement of breast cancer-related arm lymphoedema using perometry and bioimpedance spectroscopy. Support Care Cancer. 2011;19:703&#x2013;10. 10.1007/s00520-010-0896-8</Citation><ArticleIdList><ArticleId IdType="doi">10.1007/s00520-010-0896-8</ArticleId><ArticleId IdType="pubmed">20467755</ArticleId></ArticleIdList></Reference></ReferenceList></PubmedData></PubmedArticle></PubmedArticleSet>